{
  "hash": "b74b565c",
  "configHash": "662ed419",
  "lockfileHash": "6f038128",
  "browserHash": "4011512e",
  "optimized": {
    "react": {
      "src": "../../node_modules/react/index.js",
      "file": "react.js",
      "fileHash": "c5adb7ea",
      "needsInterop": true
    },
    "react-dom": {
      "src": "../../node_modules/react-dom/index.js",
      "file": "react-dom.js",
      "fileHash": "e767680d",
      "needsInterop": true
    },
    "react/jsx-dev-runtime": {
      "src": "../../node_modules/react/jsx-dev-runtime.js",
      "file": "react_jsx-dev-runtime.js",
      "fileHash": "54b11971",
      "needsInterop": true
    },
    "react/jsx-runtime": {
      "src": "../../node_modules/react/jsx-runtime.js",
      "file": "react_jsx-runtime.js",
      "fileHash": "52e7d0ff",
      "needsInterop": true
    }
  },
  "chunks": {
    "chunk-Y455YYDO": {
      "file": "chunk-Y455YYDO.js"
    }
  }
}